README.rst
setup.py
scram.egg-info/PKG-INFO
scram.egg-info/SOURCES.txt
scram.egg-info/dependency_links.txt
scram.egg-info/not-zip-safe
scram.egg-info/requires.txt
scram.egg-info/top_level.txt
scram_modules/__init__.py
scram_modules/alignedreads.py
scram_modules/analysis.py
scram_modules/analysis_helper.py
scram_modules/cdp.py
scram_modules/den.py
scram_modules/dna.py
scram_modules/plot_reads.py
scram_modules/post_process.py
scram_modules/refseq.py
scram_modules/scram
scram_modules/srnaseq.py
scram_modules/write_to_file.py