Metadata-Version: 1.1
Name: scram
Version: 0.6.3
Summary:  Small Complementary RnA Mapper
Home-page: https://github.com/Carroll-Lab/scram
Author: Stephen Fletcher
Author-email: s.fletcher@uq.edu.au
License: MIT
Platform: UNKNOWN
Classifier: Development Status :: 4 - Beta
Classifier: Intended Audience :: Science/Research
Classifier: Topic :: Scientific/Engineering :: Bio-Informatics
Classifier: License :: OSI Approved :: MIT License
Classifier: Programming Language :: Python :: 3.5
